{
  "id": "0680224b-c6b9-419d-9f23-f4bd99e1571b",
  "prevId": "180f6199-2f85-4dd3-b8f2-892a8d2dbf52",
  "version": "7",
  "dialect": "postgresql",
  "tables": {
    "public.attachments": {
      "name": "attachments",
      "schema": "",
      "columns": {
        "id": {
          "name": "id",
          "type": "uuid",
          "primaryKey": true,
          "notNull": true,
          "default": "gen_random_uuid()"
        },
        "expense_id": {
          "name": "expense_id",
          "type": "uuid",
          "primaryKey": false,
          "notNull": true
        },
        "filename": {
          "name": "filename",
          "type": "varchar(255)",
          "primaryKey": false,
          "notNull": true
        },
        "content_type": {
          "name": "content_type",
          "type": "varchar(100)",
          "primaryKey": false,
          "notNull": true
        },
        "size": {
          "name": "size",
          "type": "bigint",
          "primaryKey": false,
          "notNull": true
        },
        "data": {
          "name": "data",
          "type": "bytea",
          "primaryKey": false,
          "notNull": true
        },
        "created_at": {
          "name": "created_at",
          "type": "timestamp with time zone",
          "primaryKey": false,
          "notNull": true,
          "default": "now()"
        }
      },
      "indexes": {},
      "foreignKeys": {
        "attachments_expense_id_expenses_id_fk": {
          "name": "attachments_expense_id_expenses_id_fk",
          "tableFrom": "attachments",
          "tableTo": "expenses",
          "columnsFrom": ["expense_id"],
          "columnsTo": ["id"],
          "onDelete": "cascade",
          "onUpdate": "no action"
        }
      },
      "compositePrimaryKeys": {},
      "uniqueConstraints": {},
      "policies": {},
      "checkConstraints": {},
      "isRLSEnabled": false
    },
    "public.expenses": {
      "name": "expenses",
      "schema": "",
      "columns": {
        "id": {
          "name": "id",
          "type": "uuid",
          "primaryKey": true,
          "notNull": true,
          "default": "gen_random_uuid()"
        },
        "user_id": {
          "name": "user_id",
          "type": "uuid",
          "primaryKey": false,
          "notNull": true
        },
        "amount": {
          "name": "amount",
          "type": "numeric(19, 4)",
          "primaryKey": false,
          "notNull": true
        },
        "currency": {
          "name": "currency",
          "type": "varchar(10)",
          "primaryKey": false,
          "notNull": true
        },
        "category": {
          "name": "category",
          "type": "varchar(100)",
          "primaryKey": false,
          "notNull": true
        },
        "description": {
          "name": "description",
          "type": "varchar(500)",
          "primaryKey": false,
          "notNull": true,
          "default": "''"
        },
        "date": {
          "name": "date",
          "type": "date",
          "primaryKey": false,
          "notNull": true
        },
        "type": {
          "name": "type",
          "type": "varchar(20)",
          "primaryKey": false,
          "notNull": true
        },
        "quantity": {
          "name": "quantity",
          "type": "numeric(19, 4)",
          "primaryKey": false,
          "notNull": false
        },
        "unit": {
          "name": "unit",
          "type": "varchar(50)",
          "primaryKey": false,
          "notNull": false
        },
        "created_at": {
          "name": "created_at",
          "type": "timestamp with time zone",
          "primaryKey": false,
          "notNull": true,
          "default": "now()"
        },
        "created_by": {
          "name": "created_by",
          "type": "varchar(255)",
          "primaryKey": false,
          "notNull": true,
          "default": "'system'"
        },
        "updated_at": {
          "name": "updated_at",
          "type": "timestamp with time zone",
          "primaryKey": false,
          "notNull": true,
          "default": "now()"
        },
        "updated_by": {
          "name": "updated_by",
          "type": "varchar(255)",
          "primaryKey": false,
          "notNull": true,
          "default": "'system'"
        },
        "deleted_at": {
          "name": "deleted_at",
          "type": "timestamp with time zone",
          "primaryKey": false,
          "notNull": false
        },
        "deleted_by": {
          "name": "deleted_by",
          "type": "varchar(255)",
          "primaryKey": false,
          "notNull": false
        }
      },
      "indexes": {},
      "foreignKeys": {
        "expenses_user_id_users_id_fk": {
          "name": "expenses_user_id_users_id_fk",
          "tableFrom": "expenses",
          "tableTo": "users",
          "columnsFrom": ["user_id"],
          "columnsTo": ["id"],
          "onDelete": "no action",
          "onUpdate": "no action"
        }
      },
      "compositePrimaryKeys": {},
      "uniqueConstraints": {},
      "policies": {},
      "checkConstraints": {},
      "isRLSEnabled": false
    },
    "public.refresh_tokens": {
      "name": "refresh_tokens",
      "schema": "",
      "columns": {
        "id": {
          "name": "id",
          "type": "uuid",
          "primaryKey": true,
          "notNull": true,
          "default": "gen_random_uuid()"
        },
        "user_id": {
          "name": "user_id",
          "type": "uuid",
          "primaryKey": false,
          "notNull": true
        },
        "token_hash": {
          "name": "token_hash",
          "type": "varchar(255)",
          "primaryKey": false,
          "notNull": true
        },
        "expires_at": {
          "name": "expires_at",
          "type": "timestamp with time zone",
          "primaryKey": false,
          "notNull": true
        },
        "revoked": {
          "name": "revoked",
          "type": "boolean",
          "primaryKey": false,
          "notNull": true,
          "default": false
        },
        "created_at": {
          "name": "created_at",
          "type": "timestamp with time zone",
          "primaryKey": false,
          "notNull": true,
          "default": "now()"
        }
      },
      "indexes": {},
      "foreignKeys": {
        "refresh_tokens_user_id_users_id_fk": {
          "name": "refresh_tokens_user_id_users_id_fk",
          "tableFrom": "refresh_tokens",
          "tableTo": "users",
          "columnsFrom": ["user_id"],
          "columnsTo": ["id"],
          "onDelete": "no action",
          "onUpdate": "no action"
        }
      },
      "compositePrimaryKeys": {},
      "uniqueConstraints": {
        "refresh_tokens_token_hash_unique": {
          "name": "refresh_tokens_token_hash_unique",
          "nullsNotDistinct": false,
          "columns": ["token_hash"]
        }
      },
      "policies": {},
      "checkConstraints": {},
      "isRLSEnabled": false
    },
    "public.revoked_tokens": {
      "name": "revoked_tokens",
      "schema": "",
      "columns": {
        "id": {
          "name": "id",
          "type": "uuid",
          "primaryKey": true,
          "notNull": true,
          "default": "gen_random_uuid()"
        },
        "jti": {
          "name": "jti",
          "type": "varchar(255)",
          "primaryKey": false,
          "notNull": true
        },
        "user_id": {
          "name": "user_id",
          "type": "uuid",
          "primaryKey": false,
          "notNull": true
        },
        "revoked_at": {
          "name": "revoked_at",
          "type": "timestamp with time zone",
          "primaryKey": false,
          "notNull": true,
          "default": "now()"
        }
      },
      "indexes": {},
      "foreignKeys": {},
      "compositePrimaryKeys": {},
      "uniqueConstraints": {
        "revoked_tokens_jti_unique": {
          "name": "revoked_tokens_jti_unique",
          "nullsNotDistinct": false,
          "columns": ["jti"]
        }
      },
      "policies": {},
      "checkConstraints": {},
      "isRLSEnabled": false
    },
    "public.users": {
      "name": "users",
      "schema": "",
      "columns": {
        "id": {
          "name": "id",
          "type": "uuid",
          "primaryKey": true,
          "notNull": true,
          "default": "gen_random_uuid()"
        },
        "username": {
          "name": "username",
          "type": "varchar(50)",
          "primaryKey": false,
          "notNull": true
        },
        "password_hash": {
          "name": "password_hash",
          "type": "varchar(255)",
          "primaryKey": false,
          "notNull": true
        },
        "email": {
          "name": "email",
          "type": "varchar(255)",
          "primaryKey": false,
          "notNull": true
        },
        "display_name": {
          "name": "display_name",
          "type": "varchar(255)",
          "primaryKey": false,
          "notNull": true,
          "default": "''"
        },
        "role": {
          "name": "role",
          "type": "varchar(20)",
          "primaryKey": false,
          "notNull": true,
          "default": "'USER'"
        },
        "status": {
          "name": "status",
          "type": "varchar(20)",
          "primaryKey": false,
          "notNull": true,
          "default": "'ACTIVE'"
        },
        "failed_login_attempts": {
          "name": "failed_login_attempts",
          "type": "integer",
          "primaryKey": false,
          "notNull": true,
          "default": 0
        },
        "password_reset_token": {
          "name": "password_reset_token",
          "type": "varchar(255)",
          "primaryKey": false,
          "notNull": false
        },
        "created_at": {
          "name": "created_at",
          "type": "timestamp with time zone",
          "primaryKey": false,
          "notNull": true,
          "default": "now()"
        },
        "created_by": {
          "name": "created_by",
          "type": "varchar(255)",
          "primaryKey": false,
          "notNull": true,
          "default": "'system'"
        },
        "updated_at": {
          "name": "updated_at",
          "type": "timestamp with time zone",
          "primaryKey": false,
          "notNull": true,
          "default": "now()"
        },
        "updated_by": {
          "name": "updated_by",
          "type": "varchar(255)",
          "primaryKey": false,
          "notNull": true,
          "default": "'system'"
        },
        "deleted_at": {
          "name": "deleted_at",
          "type": "timestamp with time zone",
          "primaryKey": false,
          "notNull": false
        },
        "deleted_by": {
          "name": "deleted_by",
          "type": "varchar(255)",
          "primaryKey": false,
          "notNull": false
        }
      },
      "indexes": {},
      "foreignKeys": {},
      "compositePrimaryKeys": {},
      "uniqueConstraints": {
        "users_username_unique": {
          "name": "users_username_unique",
          "nullsNotDistinct": false,
          "columns": ["username"]
        },
        "users_email_unique": {
          "name": "users_email_unique",
          "nullsNotDistinct": false,
          "columns": ["email"]
        }
      },
      "policies": {},
      "checkConstraints": {},
      "isRLSEnabled": false
    }
  },
  "enums": {},
  "schemas": {},
  "sequences": {},
  "roles": {},
  "policies": {},
  "views": {},
  "_meta": {
    "columns": {},
    "schemas": {},
    "tables": {}
  }
}
